{
"client":"",
"company_code":"",
"brandID":"LE",
"creationDateTime":"" ,
"changeDateTime" :"",
"alternateOrderID":"",
"customerOrderID" :"",
"giftOrderInd": "",
"Orderamount": 66.0,
"currencyCode": "D",
"OrderItemamount": 34.0,
"discountAmount": 2.0,
"Adjustmentype":"",
"Adjustmentcode": "",
"Adjustmentdescription": "",
"Adjustmentamount": 3.0,
"dropoffpoint_id":"",
"Shipmentamount":34.0,
"adr1":"",
"city":"",
"country":"",
"zip":"",
"salesTaxAmount": 3.0,
"authorizationAmount":4.9,
"payMethodName":"",
"authorizationCode":"",
"Account Suffix": "",
"BillingContactID": "",
"carrier_code": "",
"payMethodCode":"",
"payMethodType":"",
"givenName": "",
"familyName":"",
"addressLine1":"",
"addressLine2":"",
"cityName":"",
"stateProvinceCode":"",
"countryCode":"",
"postalCode": "",
"requestedDeliveryDate":"",
"customerCancelDate":"",
"code":"",
"description":""
}